{
    "data_version": 4,
    "name": "Drilbur",
    "national_dex_number": 529,
    "gender_ratio": 4,
    "egg_group_1": 5,
    "egg_group_2": 0,
    "hatch_cycles": 20,
    "catch_rate": 120,
    "child_species": 529,
    "evolutions": [
        {
            "dex_num": 530,
            "min_level": 31,
            "friendship": false,
            "day_time": 0,
            "use_item": 0,
            "held_item": 0,
            "gender": 0,
            "known_move": 0
        }
    ],
    "is_sprite_gender_based": false,
    "is_stats_gender_based": false,
    "is_form_switchable": false,
    "is_born_form_random": false,
    "default_form": {
        "name": "",
        "type_1": 5,
        "type_2": 0,
        "ability_1": 146,
        "ability_2": 159,
        "hidden_ability": 104,
        "base_hp": 60,
        "base_atk": 85,
        "base_def": 40,
        "base_spAtk": 30,
        "base_spDef": 45,
        "base_spd": 68,
        "height": 3,
        "weight": 85,
        "front_sprite_count": 80,
        "back_sprite_count": 76,
        "learnset": [
            -2,
            173,
            -2,
            446,
            -1,
            66,
            -1,
            130,
            -1,
            306,
            -1,
            319,
            -1,
            334,
            -1,
            414,
            -1,
            431,
            0,
            92,
            0,
            104,
            0,
            156,
            0,
            164,
            0,
            182,
            0,
            188,
            0,
            207,
            0,
            213,
            0,
            214,
            0,
            216,
            0,
            218,
            0,
            237,
            0,
            263,
            0,
            280,
            0,
            317,
            0,
            332,
            0,
            374,
            0,
            398,
            0,
            404,
            0,
            421,
            0,
            496,
            0,
            523,
            0,
            590,
            1,
            10,
            1,
            300,
            5,
            229,
            8,
            189,
            12,
            154,
            15,
            232,
            19,
            91,
            22,
            468,
            26,
            163,
            29,
            157,
            33,
            89,
            36,
            14,
            40,
            201,
            43,
            529,
            47,
            90
        ]
    },
    "alternate_forms": [],
    "variants": []
}